{"coordinateSystem":"World space with origin at player spawn (0,0), +x right, +y down.","uiState":"levelup","timerSeconds":259.73,"player":{"x":178.7,"y":225.4,"vx":0,"vy":0,"hp":154,"maxHp":154,"level":10,"xp":0,"xpToNext":407},"counts":{"enemies":3,"enemyProjectiles":0,"hazards":0,"xpOrbs":90},"event":"verdant_fog","renderer":"webgpu","quality":"low","enemies":[{"id":10005,"x":-171.2,"y":206.8,"archetype":"moss_hound","behavior":"chaser","hp":24,"dashWindup":0,"dashDuration":0},{"id":10003,"x":651.4,"y":421.1,"archetype":"moss_hound","behavior":"chaser","hp":24,"dashWindup":0,"dashDuration":0},{"id":10001,"x":751.9,"y":339.8,"archetype":"briar_lancer","behavior":"dash_striker","hp":52,"dashWindup":0,"dashDuration":0}],"enemyProjectiles":[],"hazards":[]}