{"coordinateSystem":"World space with origin at player spawn (0,0), +x right, +y down.","uiState":"playing","timerSeconds":128.08,"player":{"x":256.6,"y":59.6,"vx":0,"vy":0,"hp":130,"maxHp":130,"level":4,"xp":39,"xpToNext":95},"counts":{"enemies":1,"enemyProjectiles":0,"hazards":0,"xpOrbs":91},"event":null,"renderer":"webgpu","quality":"low","enemies":[{"id":10001,"x":-0.8,"y":667.1,"archetype":"brambleling","behavior":"chaser","hp":34,"spitCooldown":0,"dashWindup":0,"dashDuration":0}],"enemyProjectiles":[],"hazards":[]}