{"coordinateSystem":"World space with origin at player spawn (0,0), +x right, +y down.","uiState":"playing","timerSeconds":67.12,"player":{"x":-38.4,"y":-14.2,"vx":0,"vy":0,"hp":130,"maxHp":130,"level":2,"xp":7,"xpToNext":39},"counts":{"enemies":2,"enemyProjectiles":0,"hazards":0,"xpOrbs":56},"event":null,"renderer":"webgpu","quality":"low","enemies":[{"id":10003,"x":299.6,"y":-386.3,"archetype":"moss_hound","behavior":"chaser","hp":24,"spitCooldown":0,"dashWindup":0,"dashDuration":0},{"id":10002,"x":67.9,"y":502.3,"archetype":"moss_hound","behavior":"chaser","hp":24,"spitCooldown":0,"dashWindup":0,"dashDuration":0}],"enemyProjectiles":[],"hazards":[]}