{"coordinateSystem":"World space with origin at player spawn (0,0), +x right, +y down.","uiState":"playing","timerSeconds":8.78,"player":{"x":-557.1,"y":-548,"vx":0,"vy":0,"hp":116,"maxHp":170,"level":1,"xp":32,"xpToNext":40},"director":{"phase":"awakening","intensity":0.81,"heat":0,"targetEnemies":13,"targetThreat":16.1},"inventory":[{"slot":1,"itemId":"rootspark_wand","rank":1,"evolved":false},{"slot":2,"itemId":null,"rank":0,"evolved":false},{"slot":3,"itemId":null,"rank":0,"evolved":false},{"slot":4,"itemId":null,"rank":0,"evolved":false}],"catalysts":[],"evolutionCandidates":[],"counts":{"enemies":20,"enemyProjectiles":0,"hazards":0,"chests":0,"xpOrbs":1},"event":null,"renderer":"webgpu","quality":"low","enemies":[{"id":10028,"x":-556.9,"y":-548,"archetype":"brambleling","behavior":"chaser","hp":34,"spitCooldown":0,"dashWindup":0,"dashDuration":0},{"id":10024,"x":-557,"y":-548.4,"archetype":"brambleling","behavior":"chaser","hp":16,"spitCooldown":0,"dashWindup":0,"dashDuration":0},{"id":10023,"x":-556.4,"y":-549.2,"archetype":"moss_hound","behavior":"chaser","hp":10,"spitCooldown":0,"dashWindup":0,"dashDuration":0},{"id":10032,"x":-556.8,"y":-546.3,"archetype":"brambleling","behavior":"chaser","hp":34,"spitCooldown":0,"dashWindup":0,"dashDuration":0},{"id":10022,"x":-576.9,"y":-546.6,"archetype":"moss_hound","behavior":"chaser","hp":28,"spitCooldown":0,"dashWindup":0,"dashDuration":0},{"id":10029,"x":-564,"y":-507.7,"archetype":"brambleling","behavior":"chaser","hp":34,"spitCooldown":0,"dashWindup":0,"dashDuration":0},{"id":10026,"x":-616.6,"y":-470.9,"archetype":"brambleling","behavior":"chaser","hp":34,"spitCooldown":0,"dashWindup":0,"dashDuration":0},{"id":10027,"x":-504.1,"y":-463.5,"archetype":"brambleling","behavior":"chaser","hp":34,"spitCooldown":0,"dashWindup":0,"dashDuration":0},{"id":10035,"x":-666.2,"y":-496.7,"archetype":"moss_hound","behavior":"chaser","hp":28,"spitCooldown":0,"dashWindup":0,"dashDuration":0},{"id":10021,"x":-534.8,"y":-391.9,"archetype":"brambleling","behavior":"chaser","hp":34,"spitCooldown":0,"dashWindup":0,"dashDuration":0},{"id":10031,"x":-675.1,"y":-435.2,"archetype":"brambleling","behavior":"chaser","hp":34,"spitCooldown":0,"dashWindup":0,"dashDuration":0},{"id":10020,"x":-453.5,"y":-345.3,"archetype":"brambleling","behavior":"chaser","hp":34,"spitCooldown":0,"dashWindup":0,"dashDuration":0},{"id":10034,"x":-765.7,"y":-711.7,"archetype":"moss_hound","behavior":"chaser","hp":28,"spitCooldown":0,"dashWindup":0,"dashDuration":0},{"id":10033,"x":-703,"y":-315.6,"archetype":"brambleling","behavior":"chaser","hp":34,"spitCooldown":0,"dashWindup":0,"dashDuration":0},{"id":10036,"x":-282.4,"y":-477.5,"archetype":"moss_hound","behavior":"chaser","hp":28,"spitCooldown":0,"dashWindup":0,"dashDuration":0},{"id":10025,"x":-846.6,"y":-734.8,"archetype":"brambleling","behavior":"chaser","hp":34,"spitCooldown":0,"dashWindup":0,"dashDuration":0},{"id":10037,"x":-183.4,"y":-509.4,"archetype":"brambleling","behavior":"chaser","hp":34,"spitCooldown":0,"dashWindup":0,"dashDuration":0},{"id":10038,"x":-586.9,"y":-1019.8,"archetype":"brambleling","behavior":"chaser","hp":34,"spitCooldown":0,"dashWindup":0,"dashDuration":0},{"id":10039,"x":-1044.7,"y":-274.9,"archetype":"brambleling","behavior":"chaser","hp":34,"spitCooldown":0,"dashWindup":0,"dashDuration":0},{"id":10030,"x":60.9,"y":-788.4,"archetype":"brambleling","behavior":"chaser","hp":34,"spitCooldown":0,"dashWindup":0,"dashDuration":0}],"enemyProjectiles":[],"hazards":[],"chests":[]}